Workbook

Sheet Pivot_Summaries
A1: Pivot-Style Summaries (Formula-Based)
A3: Bank Deposits by Reconciled Status
A5: Status | B5: Count | C5: Total Amount
A6: Yes | B6: =COUNTIFS(tblBankDeposits[Reconciled?],"Yes") -> 0 | C6: =SUMIFS(tblBankDeposits[Amount],tblBankDeposits[Reconciled?],"Yes") -> 0
A7: No | B7: =COUNTIFS(tblBankDeposits[Reconciled?],"No") -> 0 | C7: =SUMIFS(tblBankDeposits[Amount],tblBankDeposits[Reconciled?],"No") -> 0
A8: Investigate | B8: =COUNTIFS(tblBankDeposits[Reconciled?],"Investigate") -> 0 | C8: =SUMIFS(tblBankDeposits[Amount],tblBankDeposits[Reconciled?],"Investigate") -> 0
A10: Credit Card Payments: Variance Summary
A12: Metric | B12: Value
A13: Total Payments | B13: =COUNTA(tblCardPayments[Amount]) -> 12
A14: Matched (Variance=0) | B14: =COUNTIF(tblCardPayments[Variance],0) -> 7
A15: Exceptions (Variance≠0) | B15: =COUNTIF(tblCardPayments[Variance],"<>0") -> 5
A16: Total Variance | B16: =SUM(tblCardPayments[Variance]) -> -1.08
A18: Collections Aging Buckets
A20: Aging Bucket | B20: Count | C20: Total Owing
A21: 0–30 | B21: =COUNTIFS(tblCollections[Aging Bucket],"0–30") -> 0 | C21: =SUMIFS(tblCollections[Amount Owing],tblCollections[Aging Bucket],"0–30") -> 0
A22: 31–60 | B22: =COUNTIFS(tblCollections[Aging Bucket],"31–60") -> 0 | C22: =SUMIFS(tblCollections[Amount Owing],tblCollections[Aging Bucket],"31–60") -> 0
A23: 61–90 | B23: =COUNTIFS(tblCollections[Aging Bucket],"61–90") -> 0 | C23: =SUMIFS(tblCollections[Amount Owing],tblCollections[Aging Bucket],"61–90") -> 0
A24: 90+ | B24: =COUNTIFS(tblCollections[Aging Bucket],"90+") -> 4 | C24: =SUMIFS(tblCollections[Amount Owing],tblCollections[Aging Bucket],"90+") -> 2829.2

Sheet Bank_Deposits
A1: Date | B1: Deposit ID | C1: Amount | D1: Source | E1: Bank Statement Amount | F1: Reconciled? | G1: Variance | H1: Column1 | I1: KPIs
A2: 46057 | B2: BD-20260204-01 | C2: 4211.16 | D2: Other Receipts | E2: 4211.16 | F2: =IF(ROUND(G2,2)=0,"Y","N") -> Y | G2: =E2-C2 -> 0 | I2: Total Deposits | J2: =SUM(C2:C100) -> 28130.45
A3: 46058 | B3: BD-20260205-02 | C3: 3987.3 | D3: Employer Premiums | E3: 3987.3 | F3: =IF(ROUND(G3,2)=0,"Y","N") -> Y | G3: =E3-C3 -> 0 | I3: Reconciled % | J3: =IF(COUNTIF(F2:F1000,"Y")+COUNTIF(F2:F1000,"N")=0,0,COUNTIF(F2:F1000,"Y")/(COUNTIF(F2:F1000,"Y")+COUNTIF(F2:F1000,"N"))) -> 0.8
A4: 46059 | B4: BD-20260206-03 | C4: 849.17 | D4: Other Receipts | E4: 849.17 | F4: =IF(ROUND(G4,2)=0,"Y","N") -> Y | G4: =E4-C4 -> 0
A5: 46060 | B5: BD-20260207-04 | C5: 3473.31 | D5: Investment Income | E5: 3473.31 | F5: =IF(ROUND(G5,2)=0,"Y","N") -> Y | G5: =E5-C5 -> 0
A6: 46061 | B6: BD-20260208-05 | C6: 3746.91 | D6: Other Receipts | E6: 3758.14 | F6: =IF(ROUND(G6,2)=0,"Y","N") -> N | G6: =E6-C6 -> 11.23
A7: 46062 | B7: BD-20260209-06 | C7: 1171.2 | D7: Other Receipts | E7: 1171.2 | F7: =IF(ROUND(G7,2)=0,"Y","N") -> Y | G7: =E7-C7 -> 0
A8: 46063 | B8: BD-20260210-07 | C8: 1156.25 | D8: Other Receipts | E8: 1156.25 | F8: =IF(ROUND(G8,2)=0,"Y","N") -> Y | G8: =E8-C8 -> 0
A9: 46064 | B9: BD-20260211-08 | C9: 3148.1 | D9: Investment Income | E9: 3148.1 | F9: =IF(ROUND(G9,2)=0,"Y","N") -> Y | G9: =E9-C9 -> 0
A10: 46065 | B10: BD-20260212-09 | C10: 3722.86 | D10: Employer Premiums | E10: 3722.86 | F10: =IF(ROUND(G10,2)=0,"Y","N") -> Y | G10: =E10-C10 -> 0
A11: 46066 | B11: BD-20260213-10 | C11: 2664.19 | D11: Other Receipts | E11: 2623.7 | F11: =IF(ROUND(G11,2)=0,"Y","N") -> N | G11: =E11-C11 -> -40.49

Sheet Direct_Deposits
A1: Payee | B1: Payment Date | C1: Amount | D1: Method | E1: Reference | F1: Status | G1: Cleared Date | H1: Days to Clear
A2: Vendor/Employee 1 | B2: 46058 | C2: 1397.13 | D2: EFT | E2: DD-0001 | F2: Cleared | G2: 46061 | H2: =IF(G2="","",G2-B2) -> 3
A3: Vendor/Employee 2 | B3: 46052 | C3: 218.22 | D3: EFT | E3: DD-0002 | F3: Cleared | G3: 46054 | H3: =IF(G3="","",G3-B3) -> 2
A4: Vendor/Employee 3 | B4: 46062 | C4: 390.35 | D4: Direct Deposit | E4: DD-0003 | F4: Cleared | G4: 46066 | H4: =IF(G4="","",G4-B4) -> 4
A5: Vendor/Employee 4 | B5: 46064 | C5: 155.19 | D5: Direct Deposit | E5: DD-0004 | F5: Cleared | G5: 46068 | H5: =IF(G5="","",G5-B5) -> 4
A6: Vendor/Employee 5 | B6: 46058 | C6: 786.67 | D6: EFT | E6: DD-0005 | F6: Scheduled | H6: =IF(G6="","",G6-B6)
A7: Vendor/Employee 6 | B7: 46051 | C7: 1034.59 | D7: EFT | E7: DD-0006 | F7: Returned | H7: =IF(G7="","",G7-B7)
A8: Vendor/Employee 7 | B8: 46063 | C8: 1372.91 | D8: EFT | E8: DD-0007 | F8: Cleared | G8: 46063 | H8: =IF(G8="","",G8-B8) -> 0
A9: Vendor/Employee 8 | B9: 46065 | C9: 2426.7 | D9: EFT | E9: DD-0008 | F9: Returned | H9: =IF(G9="","",G9-B9)
A10: Vendor/Employee 9 | B10: 46055 | C10: 108.61 | D10: EFT | E10: DD-0009 | F10: Cleared | G10: 46059 | H10: =IF(G10="","",G10-B10) -> 4
A11: Vendor/Employee 10 | B11: 46047 | C11: 2335.61 | D11: Direct Deposit | E11: DD-0010 | F11: Returned | H11: =IF(G11="","",G11-B11)

Sheet CreditCard_Payments
A1: Date | B1: Transaction ID | C1: Payer | D1: Amount | E1: Card Type | F1: Auth Code | G1: Processor Amount | H1: Reconciled? | I1: Variance
A2: 46065 | B2: CC-20260212-001 | C2: Client 34 | D2: 27.35 | E2: Mastercard | F2: 854604 | G2: 27.35 | H2: =IF(ROUND(I2,2)=0,"Y","N") -> Y | I2: =G2-D2 -> 0
A3: 46062 | B3: CC-20260209-002 | C3: Client 12 | D3: 228.86 | E3: Mastercard | F3: 722365 | G3: 228.86 | H3: =IF(ROUND(I3,2)=0,"Y","N") -> Y | I3: =G3-D3 -> 0
A4: 46059 | B4: CC-20260206-003 | C4: Client 19 | D4: 86.47 | E4: Amex | F4: 423777 | G4: 86.47 | H4: =IF(ROUND(I4,2)=0,"Y","N") -> Y | I4: =G4-D4 -> 0
A5: 46042 | B5: CC-20260120-004 | C5: Client 20 | D5: 234.63 | E5: Amex | F5: 130957 | G5: 230.95 | H5: =IF(ROUND(I5,2)=0,"Y","N") -> N | I5: =G5-D5 -> -3.68
A6: 46067 | B6: CC-20260214-005 | C6: Client 30 | D6: 189.67 | E6: Amex | F6: 469713 | G6: 189.67 | H6: =IF(ROUND(I6,2)=0,"Y","N") -> Y | I6: =G6-D6 -> 0
A7: 46065 | B7: CC-20260212-006 | C7: Client 3 | D7: 17.76 | E7: Visa | F7: 363639 | G7: 16.55 | H7: =IF(ROUND(I7,2)=0,"Y","N") -> N | I7: =G7-D7 -> -1.21
A8: 46051 | B8: CC-20260129-007 | C8: Client 35 | D8: 332.65 | E8: Visa | F8: 586004 | G8: 336.46 | H8: =IF(ROUND(I8,2)=0,"Y","N") -> N | I8: =G8-D8 -> 3.81
A9: 46048 | B9: CC-20260126-008 | C9: Client 7 | D9: 67.16 | E9: Mastercard | F9: 596689 | G9: 67.16 | H9: =IF(ROUND(I9,2)=0,"Y","N") -> Y | I9: =G9-D9 -> 0
A10: 46067 | B10: CC-20260214-009 | C10: Client 2 | D10: 208.43 | E10: Mastercard | F10: 979499 | G10: 208.43 | H10: =IF(ROUND(I10,2)=0,"Y","N") -> Y | I10: =G10-D10 -> 0
A11: 46055 | B11: CC-20260202-010 | C11: Client 8 | D11: 245.71 | E11: Amex | F11: 223387 | G11: 245.71 | H11: =IF(ROUND(I11,2)=0,"Y","N") -> Y | I11: =G11-D11 -> 0
A12: 46055 | B12: CC-20260202-011 | C12: Client 36 | D12: 47.57 | E12: Mastercard | F12: 660163 | G12: 48.46 | H12: =IF(ROUND(I12,2)=0,"Y","N") -> N | I12: =G12-D12 -> 0.89
A13: 46066 | B13: CC-20260213-012 | C13: Client 34 | D13: 286.37 | E13: Amex | F13: 712098 | G13: 285.48 | H13: =IF(ROUND(I13,2)=0,"Y","N") -> N | I13: =G13-D13 -> -0.89

Sheet Vendor_Maintenance
A1: Vendor ID | B1: Vendor Name | C1: Email | D1: Phone | E1: Payment Method | F1: Banking on File? | G1: Last Verified | H1: Notes
A2: V-0001 | B2: Vendor 1 Ltd. | C2: vendor1@example.com | D2: (902) 555-1001 | E2: EFT | F2: Yes | G2: 45889
A3: V-0002 | B3: Vendor 2 Ltd. | C3: vendor2@example.com | D3: (902) 555-1002 | E3: EFT | F3: Yes | G3: 46052
A4: V-0003 | B4: Vendor 3 Ltd. | C4: vendor3@example.com | D4: (902) 555-1003 | E4: Wire | F4: No | G4: 45944
A5: V-0004 | B5: Vendor 4 Ltd. | C5: vendor4@example.com | D5: (902) 555-1004 | E5: Wire | F5: Yes | G5: 45989
A6: V-0005 | B6: Vendor 5 Ltd. | C6: vendor5@example.com | D6: (902) 555-1005 | E6: EFT | F6: No | G6: 45978
A7: V-0006 | B7: Vendor 6 Ltd. | C7: vendor6@example.com | D7: (902) 555-1006 | E7: EFT | F7: No | G7: 45902
A8: V-0007 | B8: Vendor 7 Ltd. | C8: vendor7@example.com | D8: (902) 555-1007 | E8: EFT | F8: Yes | G8: 45902
A9: V-0008 | B9: Vendor 8 Ltd. | C9: vendor8@example.com | D9: (902) 555-1008 | E9: Wire | F9: Yes | G9: 45998
A10: V-0009 | B10: Vendor 9 Ltd. | C10: vendor9@example.com | D10: (902) 555-1009 | E10: Wire | F10: No | G10: 46011
A11: V-0010 | B11: Vendor 10 Ltd. | C11: vendor10@example.com | D11: (902) 555-1010 | E11: EFT | F11: No | G11: 46053
A12: V-0011 | B12: Vendor 11 Ltd. | C12: vendor11@example.com | D12: (902) 555-1011 | E12: EFT | F12: No | G12: 46041
A13: V-0012 | B13: Vendor 12 Ltd. | C13: vendor12@example.com | D13: (902) 555-1012 | E13: Cheque | F13: No | G13: 46028
... A16: V-0015 | B16: Vendor 15 Ltd. | C16: vendor15@example.com | D16: (902) 555-1015 | E16: Cheque | F16: Yes | G16: 45962

Sheet Collections
A1: Account/Claim | B1: Invoice # | C1: Due Date | D1: Amount Owing | E1: Days Outstanding | F1: Aging Bucket | G1: Letter Sent? | H1: Last Contact Date | I1: Notes
A2: Account 001 | B2: INV-2026001 | C2: 46025 | D2: 1065.6 | E2: =TODAY()-C2 -> 42 | F2: =IF(E2<30,"0-29",IF(E2<60,"30-59",IF(E2<90,"60-89","90+"))) -> 30-59
A3: Account 002 | B3: INV-2026002 | C3: 46027 | D3: 1097.12 | E3: =TODAY()-C3 -> 40 | F3: =IF(E3<30,"0-29",IF(E3<60,"30-59",IF(E3<90,"60-89","90+"))) -> 30-59
A4: Account 003 | B4: INV-2026003 | C4: 45961 | D4: 350 | E4: =TODAY()-C4 -> 106 | F4: =IF(E4<30,"0-29",IF(E4<60,"30-59",IF(E4<90,"60-89","90+"))) -> 90+
A5: Account 004 | B5: INV-2026004 | C5: 45977 | D5: 219.33 | E5: =TODAY()-C5 -> 90 | F5: =IF(E5<30,"0-29",IF(E5<60,"30-59",IF(E5<90,"60-89","90+"))) -> 90+
A6: Account 005 | B6: INV-2026005 | C6: 46010 | D6: 1337.86 | E6: =TODAY()-C6 -> 57 | F6: =IF(E6<30,"0-29",IF(E6<60,"30-59",IF(E6<90,"60-89","90+"))) -> 30-59
A7: Account 006 | B7: INV-2026006 | C7: 46003 | D7: 370.95 | E7: =TODAY()-C7 -> 64 | F7: =IF(E7<30,"0-29",IF(E7<60,"30-59",IF(E7<90,"60-89","90+"))) -> 60-89 | H7: 46025
A8: Account 007 | B8: INV-2026007 | C8: 45972 | D8: 1131.78 | E8: =TODAY()-C8 -> 95 | F8: =IF(E8<30,"0-29",IF(E8<60,"30-59",IF(E8<90,"60-89","90+"))) -> 90+
A9: Account 008 | B9: INV-2026008 | C9: 46002 | D9: 146.58 | E9: =TODAY()-C9 -> 65 | F9: =IF(E9<30,"0-29",IF(E9<60,"30-59",IF(E9<90,"60-89","90+"))) -> 60-89
A10: Account 009 | B10: INV-2026009 | C10: 46041 | D10: 569.82 | E10: =TODAY()-C10 -> 26 | F10: =IF(E10<30,"0-29",IF(E10<60,"30-59",IF(E10<90,"60-89","90+"))) -> 0-29 | H10: 46049
A11: Account 010 | B11: INV-2026010 | C11: 46034 | D11: 670.69 | E11: =TODAY()-C11 -> 33 | F11: =IF(E11<30,"0-29",IF(E11<60,"30-59",IF(E11<90,"60-89","90+"))) -> 30-59
A12: Account 011 | B12: INV-2026011 | C12: 46016 | D12: 389.37 | E12: =TODAY()-C12 -> 51 | F12: =IF(E12<30,"0-29",IF(E12<60,"30-59",IF(E12<90,"60-89","90+"))) -> 30-59
A13: Account 012 | B13: INV-2026012 | C13: 46057 | D13: 1129.36 | E13: =TODAY()-C13 -> 10 | F13: =IF(E13<30,"0-29",IF(E13<60,"30-59",IF(E13<90,"60-89","90+"))) -> 0-29 | H13: 46062
A14: Account 013 | B14: INV-2026013 | C14: 45958 | D14: 1128.09 | E14: =TODAY()-C14 -> 109 | F14: =IF(E14<30,"0-29",IF(E14<60,"30-59",IF(E14<90,"60-89","90+"))) -> 90+

Sheet Dashboard
A1: Financial Transaction Reconciliation & Deposit Tracking System
A2: KPI | B2: Value | D2: How to use
A3: Total Bank Deposits | B3: =SUM(Bank_Deposits!C2:C1000) -> 28130.45 | D3: 1) Enter new transactions in each sheet. 2) Reconciled? auto-calculates from variance. 3) Yellow = needs review; Red = high risk/overdue. 4) Dashboard updates KPIs automatically.
A4: Bank Deposits Reconciled % | B4: =Bank_Deposits!J3 -> 0.8
A5: Total Direct Deposits | B5: =SUM(Direct_Deposits!C2:C1000) -> 10225.98
A6: Direct Deposits Cleared % | B6: =IF(COUNTIF(Direct_Deposits!F2:F1000,"Cleared")+COUNTIF(Direct_Deposits!F2:F1000,"Returned")+COUNTIF(Direct_Deposits!F2:F1000,"Sent")+COUNTIF(Direct_Deposits!F2:F1000,"Scheduled")=0,0,COUNTIF(Direct_Deposits!F2:F1000,"Cleared")/(COUNTIF(Direct_Deposits!F2:F1000,"Cleared")+COUNTIF(Direct_Deposits!F2:F1000,"Returned")+COUNTIF(Direct_Deposits!F2:F1000,"Sent")+COUNTIF(Direct_Deposits!F2:F1000,"Scheduled"))) -> 0.6
A7: Total Credit Card Payments | B7: =SUM(CreditCard_Payments!D2:D2000) -> 1972.63
A8: Credit Card Reconciled % | B8: =IF(COUNTIF(CreditCard_Payments!H2:H2000,"Y")+COUNTIF(CreditCard_Payments!H2:H2000,"N")=0,0,COUNTIF(CreditCard_Payments!H2:H2000,"Y")/(COUNTIF(CreditCard_Payments!H2:H2000,"Y")+COUNTIF(CreditCard_Payments!H2:H2000,"N"))) -> 0.58333333
A9: Open Collections Balance | B9: =SUM(Collections!D2:D2000) -> 9606.55
A10: Vendors Needing Review (>90d) | B10: =COUNTIF(Vendor_Maintenance!G2:G2000,"<"&TODAY()-90) -> 6

Sheet Macros_Optional
A1: Optional VBA Macros (Copy into Excel -> Developer -> Visual Basic -> Insert Module)
A3: Macro 1: Clear Input Rows (keeps headers)
A4: Sub ClearTransactionInputs() 'Clears all rows below headers for key sheets (adjust ranges if needed) Dim ws As Worksheet Dim sheets As Variant sheets = Array("Bank_Deposits", "Direct_Deposits", "CreditCard_Payments", "Collections") For Each s In sheets Set ws = ThisWorkbook.Worksheets(CStr(s)) ws.Rows("2:" & ws.Rows.Count).ClearContents Next s MsgBox "Transaction inputs cleared.", vbInformation End Sub
A10: Macro 2: Refresh All (if you add PivotTables in Excel)
A11: Sub RefreshAllData() ThisWorkbook.RefreshAll MsgBox "Refresh complete.", vbInformation End Sub
